MANIFEST.in
README.txt
setup.py
NetGrasp.egg-info/PKG-INFO
NetGrasp.egg-info/SOURCES.txt
NetGrasp.egg-info/dependency_links.txt
NetGrasp.egg-info/requires.txt
NetGrasp.egg-info/top_level.txt
bin/netgrasp
docs/README.md
netgrasp/__init__.py
netgrasp/netgrasp.py
netgrasp/template.netgrasp.cfg
netgrasp.egg-info/PKG-INFO
netgrasp.egg-info/SOURCES.txt
netgrasp.egg-info/dependency_links.txt
netgrasp.egg-info/requires.txt
netgrasp.egg-info/top_level.txt
netgrasp/config/__init__.py
netgrasp/config/config.py
netgrasp/database/__init__.py
netgrasp/database/database.py
netgrasp/mail_templates/TODO.txt
netgrasp/mail_templates/template.alert.base.html
netgrasp/mail_templates/template.alert.base.txt
netgrasp/mail_templates/template.alert.changed_ip.html
netgrasp/mail_templates/template.alert.changed_ip.subject.txt
netgrasp/mail_templates/template.alert.default.html
netgrasp/mail_templates/template.alert.default.subject.txt
netgrasp/mail_templates/template.alert.default.txt
netgrasp/mail_templates/template.alert.device_stale.html
netgrasp/mail_templates/template.alert.device_stale.subject.txt
netgrasp/mail_templates/template.alert.duplicate_ip.html
netgrasp/mail_templates/template.alert.duplicate_ip.subject.txt
netgrasp/mail_templates/template.alert.duplicate_mac.html
netgrasp/mail_templates/template.alert.duplicate_mac.subject.txt
netgrasp/mail_templates/template.alert.first_requested_ip.html
netgrasp/mail_templates/template.alert.first_requested_ip.subject.txt
netgrasp/mail_templates/template.alert.first_requested_ip_recently.html
netgrasp/mail_templates/template.alert.first_requested_ip_recently.subject.txt
netgrasp/mail_templates/template.alert.first_seen_device.html
netgrasp/mail_templates/template.alert.first_seen_device.subject.txt
netgrasp/mail_templates/template.alert.first_seen_device_recently.html
netgrasp/mail_templates/template.alert.first_seen_device_recently.subject.txt
netgrasp/mail_templates/template.alert.request_stale.html
netgrasp/mail_templates/template.alert.request_stale.subject.txt
netgrasp/mail_templates/template.alert.requested_ip.html
netgrasp/mail_templates/template.alert.requested_ip.subject.txt
netgrasp/mail_templates/template.alert.seen_device.html
netgrasp/mail_templates/template.alert.seen_device.subject.txt
netgrasp/mail_templates/template.digest.base.html
