Metadata-Version: 1.1
Name: NetGrasp
Version: 0.9.4
Summary: A passive network scanner
Home-page: https://github.com/jeremyandrews/netgrasp
Author: Jeremy Andrews
Author-email: jeremy@tag1consulting.com
License: 2-clause BSD
Download-URL: https://github.com/jeremyandrews/netgrasp/archive/v0.9.4-beta.tar.gz
Platform: UNKNOWN
